{
	"format_version": "1.12.0",
	"minecraft:geometry": [
		{
			"description": {
				"identifier": "geometry.unknown",
				"texture_width": 128,
				"texture_height": 128,
				"visible_bounds_width": 9,
				"visible_bounds_height": 8,
				"visible_bounds_offset": [0, 3, 0]
			},
			"bones": [
				{
					"name": "Rotation",
					"pivot": [0, 0, 0]
				},
				{
					"name": "Torso",
					"parent": "Rotation",
					"pivot": [0, 42, 0],
					"cubes": [
						{"origin": [-5, 42, -3], "size": [10, 18, 6], "uv": [65, 91]},
						{"origin": [-7, 60, -4], "size": [14, 4, 8], "uv": [64, 39]},
						{"origin": [-7, 60, -5], "size": [14, 4, 10], "uv": [64, 51]},
						{"origin": [-6, 42, -4], "size": [12, 18, 8], "uv": [64, 65]},
						{"origin": [-9, 53, 0], "size": [18, 8, 0], "uv": [0, 11]}
					]
				},
				{
					"name": "Bone_Neck",
					"parent": "Torso",
					"pivot": [0, 64, 0],
					"cubes": [
						{"origin": [-5, 65, -5], "size": [10, 10, 10], "uv": [64, 0]},
						{"origin": [-4, 64, -4], "size": [8, 5, 8], "uv": [64, 20]}
					]
				},
				{
					"name": "Left_Shoulder",
					"parent": "Torso",
					"pivot": [9, 62, 0],
					"rotation": [0, 0, 72.5],
					"cubes": [
						{"origin": [7, 60, -3], "size": [4, 4, 6], "pivot": [9, 62, 0], "rotation": [0, 0, -15], "uv": [0, 0]},
						{"origin": [11, 61, -2], "size": [18, 3, 4], "uv": [0, 19]},
						{"origin": [10, 60, -3], "size": [20, 5, 6], "uv": [0, 26]}
					]
				},
				{
					"name": "LeftElbow",
					"parent": "Left_Shoulder",
					"pivot": [29, 62.5, 0],
					"rotation": [0, 0, 22.5],
					"cubes": [
						{"origin": [29, 62, -1], "size": [18, 2, 2], "uv": [0, 44]}
					]
				},
				{
					"name": "LeftHand",
					"parent": "LeftElbow",
					"pivot": [47, 63, 0],
					"cubes": [
						{"origin": [47, 58, 0], "size": [8, 6, 0], "uv": [0, 48]},
						{"origin": [47, 58, 0.5], "size": [8, 6, 0], "pivot": [47, 63, 0], "rotation": [0, 0, 15], "uv": [0, 48]},
						{"origin": [47.3, 58, 0.9], "size": [6, 6, 0], "pivot": [47, 63, 0], "rotation": [0, 0, 35], "uv": [14, 48]},
						{"origin": [47, 57, -0.5], "size": [10, 7, 0], "uv": [0, 55]},
						{"origin": [45, 57, -1], "size": [10, 7, 0], "pivot": [47, 63, 0], "rotation": [0, 0, 17.5], "uv": [0, 62]}
					]
				},
				{
					"name": "Right_Shoulder",
					"parent": "Torso",
					"pivot": [-9, 62, 0],
					"rotation": [0, 0, -72.5],
					"cubes": [
						{"origin": [-11, 60, -3], "size": [4, 4, 6], "pivot": [-9, 62, 0], "rotation": [0, 0, 15], "uv": [20, 0]},
						{"origin": [-29, 61, -2], "size": [18, 3, 4], "uv": [0, 37]}
					]
				},
				{
					"name": "RightElbow",
					"parent": "Right_Shoulder",
					"pivot": [-29, 62.5, 0],
					"rotation": [0, 0, -20],
					"cubes": [
						{"origin": [-47, 62, -1], "size": [18, 2, 2], "uv": [0, 44]}
					]
				},
				{
					"name": "RightHand",
					"parent": "RightElbow",
					"pivot": [-47, 63, 0],
					"rotation": [0, 180, 0],
					"cubes": [
						{"origin": [-47, 58, 0], "size": [8, 6, 0], "uv": [0, 48]},
						{"origin": [-47, 58, -0.5], "size": [8, 6, 0], "pivot": [-47, 63, 0], "rotation": [0, 0, 15], "uv": [0, 48]},
						{"origin": [-46.7, 58, -0.9], "size": [6, 6, 0], "pivot": [-47, 63, 0], "rotation": [0, 0, 35], "uv": [14, 48]},
						{"origin": [-47, 57, 0.5], "size": [10, 7, 0], "uv": [0, 55]},
						{"origin": [-49, 57, 1], "size": [10, 7, 0], "pivot": [-47, 63, 0], "rotation": [0, 0, 17.5], "uv": [0, 62]}
					]
				},
				{
					"name": "Left_Leg",
					"parent": "Rotation",
					"pivot": [3, 42, 0],
					"cubes": [
						{"origin": [2, 21, -1], "size": [3, 21, 2], "uv": [105, 0]}
					]
				},
				{
					"name": "Knee",
					"parent": "Left_Leg",
					"pivot": [3, 21, 1],
					"cubes": [
						{"origin": [2, 0, -1], "size": [3, 21, 2], "uv": [115, 0]}
					]
				},
				{
					"name": "Right_Leg",
					"parent": "Rotation",
					"pivot": [-3, 42, 0],
					"cubes": [
						{"origin": [-5, 21, -1], "size": [3, 21, 2], "uv": [105, 0]}
					]
				},
				{
					"name": "Knee2",
					"parent": "Right_Leg",
					"pivot": [-3, 21, 1],
					"cubes": [
						{"origin": [-4, 0, 1], "size": [3, 21, 2], "pivot": [-3, 43, 1], "rotation": [0, 180, 0], "uv": [115, 0]}
					]
				}
			]
		}
	]
}