{
   "format_version": "1.12.0",
   "minecraft:geometry": [
      {
         "description": {
            "identifier": "geometry.slenderman",
            "texture_width": 128,
            "texture_height": 128,
            "visible_bounds_width": 9,
            "visible_bounds_height": 10,
            "visible_bounds_offset": [ 0, 4, 0 ]
         },
         "bones": [
            {
               "name": "slenderman",
               "pivot": [ 0, 15.48, 0 ]
            },
            {
               "name": "chest",
               "parent": "slenderman",
               "pivot": [ 0, 33.012, 0 ],
               "cubes": [
                  {
                     "origin": [ -3.78, 33.336, -3.016 ],
                     "size": [ 7.56, 5.544, 4.032 ],
                     "pivot": [ 0, 37.656, -1 ],
                     "rotation": [ 17.5, 0, 0 ],
                     "uv": {
                        "north": { "uv": [ 8, 8 ], "uv_size": [ 15, 11 ] },
                        "east": { "uv": [ 0, 8 ], "uv_size": [ 8, 11 ] },
                        "south": { "uv": [ 31, 8 ], "uv_size": [ 15, 11 ] },
                        "west": { "uv": [ 23, 8 ], "uv_size": [ 8, 11 ] },
                        "up": { "uv": [ 8, 0 ], "uv_size": [ 15, 8 ] },
                        "down": { "uv": [ 23, 8 ], "uv_size": [ 15, -8 ] }
                     }
                  }
               ]
            },
            {
               "name": "head",
               "parent": "chest",
               "pivot": [ 0, 37.556, 0 ]
            },
            {
               "name": "face",
               "parent": "head",
               "pivot": [ 0, 40.076, 0 ],
               "cubes": [
                  {
                     "origin": [ -2, 41.896, -5.04 ],
                     "size": [ 4, 3.04, 5.544 ],
                     "uv": {
                        "north": { "uv": [ 51, 43 ], "uv_size": [ 7, 6 ] },
                        "east": { "uv": [ 43, 43 ], "uv_size": [ 8, 6 ] },
                        "south": { "uv": [ 66, 43 ], "uv_size": [ 7, 6 ] },
                        "west": { "uv": [ 58, 43 ], "uv_size": [ 8, 6 ] },
                        "up": { "uv": [ 51, 35 ], "uv_size": [ 7, 8 ] },
                        "down": { "uv": [ 58, 43 ], "uv_size": [ 7, -8 ] }
                     }
                  }
               ]
            },
            {
               "name": "jaw",
               "parent": "head",
               "pivot": [ 0, 39.572, 0 ],
               "cubes": [
                  {
                     "origin": [ -2, 39.88, -4.5 ],
                     "size": [ 4, 2.016, 5 ],
                     "uv": {
                        "north": { "uv": [ 52, 65 ], "uv_size": [ 6, 4 ] },
                        "east": { "uv": [ 45, 65 ], "uv_size": [ 7, 4 ] },
                        "south": { "uv": [ 65, 65 ], "uv_size": [ 6, 4 ] },
                        "west": { "uv": [ 58, 65 ], "uv_size": [ 7, 4 ] },
                        "up": { "uv": [ 52, 58 ], "uv_size": [ 6, 7 ] },
                        "down": { "uv": [ 58, 65 ], "uv_size": [ 6, -7 ] }
                     }
                  },
                  {
                     "origin": [ -1.75, 38.88, -4.5 ],
                     "size": [ 3.5, 1.016, 5 ],
                     "uv": {
                        "north": { "uv": [ 79, 68 ], "uv_size": [ 6, 2 ] },
                        "east": { "uv": [ 72, 68 ], "uv_size": [ 7, 2 ] },
                        "south": { "uv": [ 92, 68 ], "uv_size": [ 6, 2 ] },
                        "west": { "uv": [ 85, 68 ], "uv_size": [ 7, 2 ] },
                        "up": { "uv": [ 79, 61 ], "uv_size": [ 6, 7 ] },
                        "down": { "uv": [ 85, 68 ], "uv_size": [ 6, -7 ] }
                     }
                  }
               ]
            },
            {
               "name": "stomach",
               "parent": "chest",
               "pivot": [ 0, 33.012, 1.764 ],
               "cubes": [
                  {
                     "origin": [ -3.024, 25.776, -1.764 ],
                     "size": [ 6.048, 8.064, 3.528 ],
                     "pivot": [ 0, 37.656, 1.764 ],
                     "rotation": [ 2.5, 0, 0 ],
                     "uv": {
                        "north": { "uv": [ 7, 27 ], "uv_size": [ 12, 16 ] },
                        "east": { "uv": [ 0, 27 ], "uv_size": [ 7, 16 ] },
                        "south": { "uv": [ 26, 27 ], "uv_size": [ 12, 16 ] },
                        "west": { "uv": [ 19, 27 ], "uv_size": [ 7, 16 ] },
                        "up": { "uv": [ 7, 20 ], "uv_size": [ 12, 7 ] },
                        "down": { "uv": [ 19, 27 ], "uv_size": [ 12, -7 ] }
                     }
                  }
               ]
            },
            {
               "name": "coattails",
               "parent": "stomach",
               "pivot": [ 0, 26.964, 1.764 ],
               "rotation": [ 7.5, 0, 0 ],
               "cubes": [
                  {
                     "origin": [ -3.276, 22.752, -0.252 ],
                     "size": [ 6.552, 5.04, 2.52 ],
                     "uv": {
                        "north": { "uv": [ 5, 52 ], "uv_size": [ 13, 10 ] },
                        "east": { "uv": [ 0, 52 ], "uv_size": [ 5, 10 ] },
                        "south": { "uv": [ 23, 52 ], "uv_size": [ 13, 10 ] },
                        "west": { "uv": [ 18, 52 ], "uv_size": [ 5, 10 ] },
                        "up": { "uv": [ 5, 47 ], "uv_size": [ 13, 5 ] },
                        "down": { "uv": [ 18, 52 ], "uv_size": [ 13, -5 ] }
                     }
                  }
               ]
            },
            {
               "name": "lLeg01",
               "parent": "chest",
               "pivot": [ 1.512, 25.452, 0.504 ],
               "rotation": [ -5, 0, -2.5 ],
               "cubes": [
                  {
                     "origin": [ 0, 13.176, -1.26 ],
                     "size": [ 3.024, 12.6, 3.024 ],
                     "uv": {
                        "north": { "uv": [ 53, 6 ], "uv_size": [ 6, 25 ] },
                        "east": { "uv": [ 47, 6 ], "uv_size": [ 6, 25 ] },
                        "south": { "uv": [ 65, 6 ], "uv_size": [ 6, 25 ] },
                        "west": { "uv": [ 59, 6 ], "uv_size": [ 6, 25 ] },
                        "up": { "uv": [ 53, 0 ], "uv_size": [ 6, 6 ] },
                        "down": { "uv": [ 59, 6 ], "uv_size": [ 6, -6 ] }
                     }
                  }
               ]
            },
            {
               "name": "lLeg02",
               "parent": "lLeg01",
               "pivot": [ 1.512, 12.852, -1.008 ],
               "rotation": [ 5, 0, 2.5 ],
               "cubes": [
                  {
                     "origin": [ 0.252, 0.072, -1.008 ],
                     "size": [ 2.52, 13.104, 2.52 ],
                     "uv": {
                        "north": { "uv": [ 78, 5 ], "uv_size": [ 5, 26 ] },
                        "east": { "uv": [ 73, 5 ], "uv_size": [ 5, 26 ] },
                        "south": { "uv": [ 88, 5 ], "uv_size": [ 5, 26 ] },
                        "west": { "uv": [ 83, 5 ], "uv_size": [ 5, 26 ] },
                        "up": { "uv": [ 78, 0 ], "uv_size": [ 5, 5 ] },
                        "down": { "uv": [ 83, 5 ], "uv_size": [ 5, -5 ] }
                     }
                  }
               ]
            },
            {
               "name": "rLeg01",
               "parent": "chest",
               "pivot": [ -1.512, 25.452, 0.504 ],
               "rotation": [ -5, 0, 2.5 ],
               "cubes": [
                  {
                     "origin": [ -3.024, 13.176, -1.26 ],
                     "size": [ 3.024, 12.6, 3.024 ],
                     "uv": {
                        "north": { "uv": [ 59, 6 ], "uv_size": [ -6, 25 ] },
                        "east": { "uv": [ 65, 6 ], "uv_size": [ -6, 25 ] },
                        "south": { "uv": [ 71, 6 ], "uv_size": [ -6, 25 ] },
                        "west": { "uv": [ 53, 6 ], "uv_size": [ -6, 25 ] },
                        "up": { "uv": [ 59, 0 ], "uv_size": [ -6, 6 ] },
                        "down": { "uv": [ 65, 6 ], "uv_size": [ -6, -6 ] }
                     }
                  }
               ]
            },
            {
               "name": "rLeg02",
               "parent": "rLeg01",
               "pivot": [ -1.512, 12.852, -1.008 ],
               "rotation": [ 5, 0, -2.5 ],
               "cubes": [
                  {
                     "origin": [ -2.772, 0.072, -1.008 ],
                     "size": [ 2.52, 13.104, 2.52 ],
                     "uv": {
                        "north": { "uv": [ 83, 5 ], "uv_size": [ -5, 26 ] },
                        "east": { "uv": [ 88, 5 ], "uv_size": [ -5, 26 ] },
                        "south": { "uv": [ 93, 5 ], "uv_size": [ -5, 26 ] },
                        "west": { "uv": [ 78, 5 ], "uv_size": [ -5, 26 ] },
                        "up": { "uv": [ 83, 0 ], "uv_size": [ -5, 5 ] },
                        "down": { "uv": [ 88, 5 ], "uv_size": [ -5, -5 ] }
                     }
                  }
               ]
            },
            {
               "name": "lArm01",
               "parent": "chest",
               "pivot": [ 3.528, 37.044, -1.512 ],
               "rotation": [ 0, -7.5, -2.5 ],
               "cubes": [
                  {
                     "origin": [ 3.528, 24.768, -2.016 ],
                     "size": [ 2.52, 13.608, 2.52 ],
                     "uv": {
                        "north": { "uv": [ 100, 5 ], "uv_size": [ 5, 27 ] },
                        "east": { "uv": [ 95, 5 ], "uv_size": [ 5, 27 ] },
                        "south": { "uv": [ 110, 5 ], "uv_size": [ 5, 27 ] },
                        "west": { "uv": [ 105, 5 ], "uv_size": [ 5, 27 ] },
                        "up": { "uv": [ 100, 0 ], "uv_size": [ 5, 5 ] },
                        "down": { "uv": [ 105, 5 ], "uv_size": [ 5, -5 ] }
                     }
                  }
               ]
            },
            {
               "name": "lArm02",
               "parent": "lArm01",
               "pivot": [ 4.536, 24.444, 0 ],
               "rotation": [ -5, 0, -2.5 ],
               "cubes": [
                  {
                     "origin": [ 3.78, 10.656, -2.016 ],
                     "size": [ 2.016, 14.112, 2.52 ],
                     "uv": {
                        "north": { "uv": [ 115, 36 ], "uv_size": [ 4, 28 ] },
                        "east": { "uv": [ 110, 36 ], "uv_size": [ 5, 28 ] },
                        "south": { "uv": [ 124, 36 ], "uv_size": [ 4, 28 ] },
                        "west": { "uv": [ 119, 36 ], "uv_size": [ 5, 28 ] },
                        "up": { "uv": [ 115, 31 ], "uv_size": [ 4, 5 ] },
                        "down": { "uv": [ 119, 36 ], "uv_size": [ 4, -5 ] }
                     }
                  }
               ]
            },
            {
               "name": "lClawsRotator",
               "parent": "lArm02",
               "pivot": [ 5.544, 10.206, 0.126 ],
               "rotation": [ 7.5, 0, 12.5 ]
            },
            {
               "name": "lClaw01",
               "parent": "lClawsRotator",
               "pivot": [ 5.544, 10.71, -1.386 ],
               "rotation": [ -7.5, 0, 0 ],
               "cubes": [
                  {
                     "origin": [ 4.536, 7.002, -1.89 ],
                     "size": [ 1.512, 5.04, 0.504 ],
                     "uv": {
                        "north": { "uv": [ 121, 1 ], "uv_size": [ 3, 10 ] },
                        "east": { "uv": [ 120, 1 ], "uv_size": [ 1, 10 ] },
                        "south": { "uv": [ 125, 1 ], "uv_size": [ 3, 10 ] },
                        "west": { "uv": [ 124, 1 ], "uv_size": [ 1, 10 ] },
                        "up": { "uv": [ 121, 0 ], "uv_size": [ 3, 1 ] },
                        "down": { "uv": [ 124, 1 ], "uv_size": [ 3, -1 ] }
                     }
                  }
               ]
            },
            {
               "name": "lClaw05",
               "parent": "lClawsRotator",
               "pivot": [ 3.528, 11.214, -1.386 ],
               "rotation": [ -7.5, 0, -7.5 ],
               "cubes": [
                  {
                     "origin": [ 2.52, 7.506, -1.89 ],
                     "size": [ 1.512, 5.04, 1.008 ],
                     "uv": {
                        "north": { "uv": [ 120, 15 ], "uv_size": [ 3, 10 ] },
                        "east": { "uv": [ 118, 15 ], "uv_size": [ 2, 10 ] },
                        "south": { "uv": [ 125, 15 ], "uv_size": [ 3, 10 ] },
                        "west": { "uv": [ 123, 15 ], "uv_size": [ 2, 10 ] },
                        "up": { "uv": [ 120, 13 ], "uv_size": [ 3, 2 ] },
                        "down": { "uv": [ 123, 15 ], "uv_size": [ 3, -2 ] }
                     }
                  }
               ]
            },
            {
               "name": "lClaw02",
               "parent": "lClawsRotator",
               "pivot": [ 5.544, 10.332, -0.756 ],
               "rotation": [ -2.5, 0, 0 ],
               "cubes": [
                  {
                     "origin": [ 4.536, 6.624, -1.26 ],
                     "size": [ 1.512, 5.04, 0.504 ],
                     "uv": {
                        "north": { "uv": [ 121, 1 ], "uv_size": [ 3, 10 ] },
                        "east": { "uv": [ 120, 1 ], "uv_size": [ 1, 10 ] },
                        "south": { "uv": [ 125, 1 ], "uv_size": [ 3, 10 ] },
                        "west": { "uv": [ 124, 1 ], "uv_size": [ 1, 10 ] },
                        "up": { "uv": [ 121, 0 ], "uv_size": [ 3, 1 ] },
                        "down": { "uv": [ 124, 1 ], "uv_size": [ 3, -1 ] }
                     }
                  }
               ]
            },
            {
               "name": "lClaw03",
               "parent": "lClawsRotator",
               "pivot": [ 5.544, 10.206, -0.126 ],
               "rotation": [ 2.5, 0, 0 ],
               "cubes": [
                  {
                     "origin": [ 4.536, 6.498, -0.63 ],
                     "size": [ 1.512, 5.04, 0.504 ],
                     "uv": {
                        "north": { "uv": [ 121, 1 ], "uv_size": [ 3, 10 ] },
                        "east": { "uv": [ 120, 1 ], "uv_size": [ 1, 10 ] },
                        "south": { "uv": [ 125, 1 ], "uv_size": [ 3, 10 ] },
                        "west": { "uv": [ 124, 1 ], "uv_size": [ 1, 10 ] },
                        "up": { "uv": [ 121, 0 ], "uv_size": [ 3, 1 ] },
                        "down": { "uv": [ 124, 1 ], "uv_size": [ 3, -1 ] }
                     }
                  }
               ]
            },
            {
               "name": "lClaw04",
               "parent": "lClawsRotator",
               "pivot": [ 5.544, 10.458, 0.63 ],
               "rotation": [ 10, 0, 0 ],
               "cubes": [
                  {
                     "origin": [ 4.536, 6.75, 0.126 ],
                     "size": [ 1.512, 5.04, 0.504 ],
                     "uv": {
                        "north": { "uv": [ 121, 1 ], "uv_size": [ 3, 10 ] },
                        "east": { "uv": [ 120, 1 ], "uv_size": [ 1, 10 ] },
                        "south": { "uv": [ 125, 1 ], "uv_size": [ 3, 10 ] },
                        "west": { "uv": [ 124, 1 ], "uv_size": [ 1, 10 ] },
                        "up": { "uv": [ 121, 0 ], "uv_size": [ 3, 1 ] },
                        "down": { "uv": [ 124, 1 ], "uv_size": [ 3, -1 ] }
                     }
                  }
               ]
            },
            {
               "name": "rArm01",
               "parent": "chest",
               "pivot": [ -3.528, 37.044, -1.512 ],
               "rotation": [ 0, 7.5, 2.5 ],
               "cubes": [
                  {
                     "origin": [ -6.048, 24.768, -2.016 ],
                     "size": [ 2.52, 13.608, 2.52 ],
                     "uv": {
                        "north": { "uv": [ 105, 5 ], "uv_size": [ -5, 27 ] },
                        "east": { "uv": [ 110, 5 ], "uv_size": [ -5, 27 ] },
                        "south": { "uv": [ 115, 5 ], "uv_size": [ -5, 27 ] },
                        "west": { "uv": [ 100, 5 ], "uv_size": [ -5, 27 ] },
                        "up": { "uv": [ 105, 0 ], "uv_size": [ -5, 5 ] },
                        "down": { "uv": [ 110, 5 ], "uv_size": [ -5, -5 ] }
                     }
                  }
               ]
            },
            {
               "name": "rArm02",
               "parent": "rArm01",
               "pivot": [ -4.536, 24.444, 0 ],
               "rotation": [ -5, 0, 2.5 ],
               "cubes": [
                  {
                     "origin": [ -5.796, 10.656, -2.016 ],
                     "size": [ 2.016, 14.112, 2.52 ],
                     "uv": {
                        "north": { "uv": [ 119, 36 ], "uv_size": [ -4, 28 ] },
                        "east": { "uv": [ 124, 36 ], "uv_size": [ -5, 28 ] },
                        "south": { "uv": [ 128, 36 ], "uv_size": [ -4, 28 ] },
                        "west": { "uv": [ 115, 36 ], "uv_size": [ -5, 28 ] },
                        "up": { "uv": [ 119, 31 ], "uv_size": [ -4, 5 ] },
                        "down": { "uv": [ 123, 36 ], "uv_size": [ -4, -5 ] }
                     }
                  }
               ]
            },
            {
               "name": "rClawsRotator",
               "parent": "rArm02",
               "pivot": [ -5.544, 10.206, 0.126 ],
               "rotation": [ 7.5, 0, -12.5 ]
            },
            {
               "name": "rClaw01",
               "parent": "rClawsRotator",
               "pivot": [ -5.544, 10.71, -1.386 ],
               "rotation": [ -7.5, 0, 0 ],
               "cubes": [
                  {
                     "origin": [ -6.048, 7.002, -1.89 ],
                     "size": [ 1.512, 5.04, 0.504 ],
                     "uv": {
                        "north": { "uv": [ 124, 1 ], "uv_size": [ -3, 10 ] },
                        "east": { "uv": [ 125, 1 ], "uv_size": [ -1, 10 ] },
                        "south": { "uv": [ 128, 1 ], "uv_size": [ -3, 10 ] },
                        "west": { "uv": [ 121, 1 ], "uv_size": [ -1, 10 ] },
                        "up": { "uv": [ 124, 0 ], "uv_size": [ -3, 1 ] },
                        "down": { "uv": [ 127, 1 ], "uv_size": [ -3, -1 ] }
                     }
                  }
               ]
            },
            {
               "name": "rClaw02",
               "parent": "rClawsRotator",
               "pivot": [ -3.528, 11.214, -1.386 ],
               "rotation": [ -7.5, 0, 7.5 ],
               "cubes": [
                  {
                     "origin": [ -4.032, 7.506, -1.89 ],
                     "size": [ 1.512, 5.04, 1.008 ],
                     "uv": {
                        "north": { "uv": [ 123, 15 ], "uv_size": [ -3, 10 ] },
                        "east": { "uv": [ 125, 15 ], "uv_size": [ -2, 10 ] },
                        "south": { "uv": [ 128, 15 ], "uv_size": [ -3, 10 ] },
                        "west": { "uv": [ 120, 15 ], "uv_size": [ -2, 10 ] },
                        "up": { "uv": [ 123, 13 ], "uv_size": [ -3, 2 ] },
                        "down": { "uv": [ 126, 15 ], "uv_size": [ -3, -2 ] }
                     }
                  }
               ]
            },
            {
               "name": "rClaw03",
               "parent": "rClawsRotator",
               "pivot": [ -5.544, 10.332, -0.756 ],
               "rotation": [ -2.5, 0, 0 ],
               "cubes": [
                  {
                     "origin": [ -6.048, 6.624, -1.26 ],
                     "size": [ 1.512, 5.04, 0.504 ],
                     "uv": {
                        "north": { "uv": [ 124, 1 ], "uv_size": [ -3, 10 ] },
                        "east": { "uv": [ 125, 1 ], "uv_size": [ -1, 10 ] },
                        "south": { "uv": [ 128, 1 ], "uv_size": [ -3, 10 ] },
                        "west": { "uv": [ 121, 1 ], "uv_size": [ -1, 10 ] },
                        "up": { "uv": [ 124, 0 ], "uv_size": [ -3, 1 ] },
                        "down": { "uv": [ 127, 1 ], "uv_size": [ -3, -1 ] }
                     }
                  }
               ]
            },
            {
               "name": "rClaw04",
               "parent": "rClawsRotator",
               "pivot": [ -5.544, 10.206, -0.126 ],
               "rotation": [ 2.5, 0, 0 ],
               "cubes": [
                  {
                     "origin": [ -6.048, 6.498, -0.63 ],
                     "size": [ 1.512, 5.04, 0.504 ],
                     "uv": {
                        "north": { "uv": [ 124, 1 ], "uv_size": [ -3, 10 ] },
                        "east": { "uv": [ 125, 1 ], "uv_size": [ -1, 10 ] },
                        "south": { "uv": [ 128, 1 ], "uv_size": [ -3, 10 ] },
                        "west": { "uv": [ 121, 1 ], "uv_size": [ -1, 10 ] },
                        "up": { "uv": [ 124, 0 ], "uv_size": [ -3, 1 ] },
                        "down": { "uv": [ 127, 1 ], "uv_size": [ -3, -1 ] }
                     }
                  }
               ]
            },
            {
               "name": "rClaw05",
               "parent": "rClawsRotator",
               "pivot": [ -5.544, 10.458, 0.63 ],
               "rotation": [ 10, 0, 0 ],
               "cubes": [
                  {
                     "origin": [ -6.048, 6.75, 0.126 ],
                     "size": [ 1.512, 5.04, 0.504 ],
                     "uv": {
                        "north": { "uv": [ 124, 1 ], "uv_size": [ -3, 10 ] },
                        "east": { "uv": [ 125, 1 ], "uv_size": [ -1, 10 ] },
                        "south": { "uv": [ 128, 1 ], "uv_size": [ -3, 10 ] },
                        "west": { "uv": [ 121, 1 ], "uv_size": [ -1, 10 ] },
                        "up": { "uv": [ 124, 0 ], "uv_size": [ -3, 1 ] },
                        "down": { "uv": [ 127, 1 ], "uv_size": [ -3, -1 ] }
                     }
                  }
               ]
            }
         ]
      }
   ]
}